djlime/__init__.py
djlime/fabfile/__init__.py
djlime/forms/__init__.py
djlime/forms/utils.py
djlime/forms/widgets.py
djlime/templatetags/__init__.py
djlime/templatetags/utils.py
djlime/utils/__init__.py
djlime/utils/mail.py
djlime/utils/pagination.py
djlime/views/__init__.py
djlime/views/robots.py
djlime-0.0.37.dist-info/DESCRIPTION.rst
djlime-0.0.37.dist-info/METADATA
djlime-0.0.37.dist-info/RECORD
djlime-0.0.37.dist-info/WHEEL
djlime-0.0.37.dist-info/metadata.json
djlime-0.0.37.dist-info/top_level.txt
