Metadata-Version: 2.0
Name: djlime
Version: 0.0.37
Summary: Django goodies.
Home-page: http://github.com/freshlimestudio/djlime/
Author: Andrey Voronov
Author-email: voronov84@gmail.com
License: BSD
Platform: UNKNOWN
Classifier: Development Status :: 3 - Alpha
Classifier: Environment :: Web Environment
Classifier: Framework :: Django
Classifier: Intended Audience :: Developers
Classifier: License :: OSI Approved :: MIT License
Classifier: Operating System :: OS Independent
Classifier: Programming Language :: Python
Classifier: Topic :: Utilities
Classifier: Topic :: Software Development :: Libraries :: Python Modules
Requires-Dist: django (>=1.5)
Requires-Dist: simplejson
